microsim/__init__.py
microsim/_data_array.py
microsim/_draw.py
microsim/_emission_bins.py
microsim/_field_types.py
microsim/_logger.py
microsim/psf.py
microsim/py.typed
microsim/util.py
microsim/xarray_jax.py
microsim/allen/__init__.py
microsim/allen/_fetch.py
microsim/allen/_swc.py
microsim/cosem/__init__.py
microsim/cosem/_client.py
microsim/cosem/_tstore.py
microsim/cosem/_xarray.py
microsim/cosem/manage.py
microsim/cosem/models.py
microsim/fft/__init__.py
microsim/fft/backends.py
microsim/fft/convolve.py
microsim/illum/__init__.py
microsim/illum/_sim.py
microsim/illum/_spinning_disc.py
microsim/schema/__init__.py
microsim/schema/_base_model.py
microsim/schema/_jax_bessel.py
microsim/schema/_validators.py
microsim/schema/backend.py
microsim/schema/dimensions.py
microsim/schema/lens.py
microsim/schema/settings.py
microsim/schema/simulation.py
microsim/schema/space.py
microsim/schema/spectrum.py
microsim/schema/detectors/__init__.py
microsim/schema/detectors/_camera.py
microsim/schema/detectors/lib.py
microsim/schema/modality/__init__.py
microsim/schema/modality/_simple_psf.py
microsim/schema/optical_config/__init__.py
microsim/schema/optical_config/config.py
microsim/schema/optical_config/filter.py
microsim/schema/optical_config/lib.py
microsim/schema/sample/__init__.py
microsim/schema/sample/fluorophore.py
microsim/schema/sample/sample.py
microsim/schema/sample/_distributions/__init__.py
microsim/schema/sample/_distributions/_base.py
microsim/schema/sample/_distributions/cosem.py
microsim/schema/sample/_distributions/direct.py
microsim/schema/sample/_distributions/matslines.py
microsim-0.0.12.dist-info/METADATA
microsim-0.0.12.dist-info/WHEEL
microsim-0.0.12.dist-info/licenses/LICENSE
microsim-0.0.12.dist-info/RECORD
