Metadata-Version: 2.4
Name: microsim
Version: 0.0.12
Summary: Light microscopy simulation in python
Project-URL: homepage, https://github.com/tlambert03/microsim
Project-URL: repository, https://github.com/tlambert03/microsim
Author-email: Talley Lambert <talley.lambert@gmail.com>
License: BSD-3-Clause
License-File: LICENSE
Classifier: Development Status :: 2 - Pre-Alpha
Classifier: License :: OSI Approved :: BSD License
Classifier: Programming Language :: Python :: 3
Classifier: Programming Language :: Python :: 3.10
Classifier: Programming Language :: Python :: 3.11
Classifier: Programming Language :: Python :: 3.12
Classifier: Typing :: Typed
Requires-Python: >=3.10
Requires-Dist: annotated-types>=0.7.0
Requires-Dist: fpbase
Requires-Dist: numpy<2.0,>=1.26
Requires-Dist: pint>=0.23
Requires-Dist: platformdirs>=4.3.6
Requires-Dist: pydantic-settings>2.5.0
Requires-Dist: pydantic>=2.8
Requires-Dist: scipy>=1.15.2
Requires-Dist: tensorstore!=0.1.72,>=0.1.70
Requires-Dist: tqdm>=4.67.1
Requires-Dist: xarray>=2024.1.0
Requires-Dist: zarr<3.0,>=2.17
Provides-Extra: all
Requires-Dist: boto3>=1.32; extra == 'all'
Requires-Dist: dask>=2024.1.0; extra == 'all'
Requires-Dist: imageio>=2.22; extra == 'all'
Requires-Dist: imageio[ffmpeg]>=2.22; extra == 'all'
Requires-Dist: matplotlib>=3.10.1; extra == 'all'
Requires-Dist: ndv[pyqt,vispy]; extra == 'all'
Requires-Dist: pyopengl-accelerate; extra == 'all'
Requires-Dist: rich>=13; extra == 'all'
Requires-Dist: s3fs>=0.4.2; extra == 'all'
Requires-Dist: supabase>=2.13.0; extra == 'all'
Requires-Dist: tifffile>=2025.2.18; extra == 'all'
Requires-Dist: xarray-datatree>=0.0.14; extra == 'all'
Provides-Extra: cosem
Requires-Dist: boto3>=1.32; extra == 'cosem'
Requires-Dist: dask>=2024.1.0; extra == 'cosem'
Requires-Dist: imageio>=2.22; extra == 'cosem'
Requires-Dist: s3fs>=0.4.2; extra == 'cosem'
Requires-Dist: supabase>=2.13.0; extra == 'cosem'
Requires-Dist: xarray-datatree>=0.0.14; extra == 'cosem'
Provides-Extra: io
Requires-Dist: imageio[ffmpeg]>=2.22; extra == 'io'
Requires-Dist: tifffile>=2025.2.18; extra == 'io'
Provides-Extra: jax
Requires-Dist: dm-tree==0.1.8; (sys_platform == 'darwin') and extra == 'jax'
Requires-Dist: dm-tree>=0.1.7; extra == 'jax'
Requires-Dist: jax[cpu]>=0.5.2; extra == 'jax'
Provides-Extra: torch
Requires-Dist: torch>=2.6.0; extra == 'torch'
Requires-Dist: torchaudio>=2.7.0; extra == 'torch'
Provides-Extra: view
Requires-Dist: matplotlib>=3.10.1; extra == 'view'
Requires-Dist: ndv[pyqt,vispy]; extra == 'view'
Requires-Dist: pyopengl-accelerate; extra == 'view'
